LICENSE
README.md
setup.py
udlayer/__init__.py
udlayer.egg-info/PKG-INFO
udlayer.egg-info/SOURCES.txt
udlayer.egg-info/dependency_links.txt
udlayer.egg-info/requires.txt
udlayer.egg-info/top_level.txt
udlayer/alignment/__init__.py
udlayer/alignment/alignment.py
udlayer/fusion/__init__.py
udlayer/fusion/fusion.py
udlayer/layer/__init__.py
udlayer/layer/base.py
udlayer/layer/graphlayer.py
udlayer/layer/gridlayer.py
udlayer/layer/linestringlayer.py
udlayer/layer/pointlayer.py
udlayer/layer/polygonlayer.py
udlayer/transformation/__init__.py
udlayer/transformation/transformation.py
udlayer/utils/__init__.py
udlayer/utils/utility.py