Metadata-Version: 2.1
Name: udlayer
Version: 0.2.1
Summary: A suite of standardized data structure and pipeline for city data engineerin
Home-page: https://github.com/SJTU-CILAB/udl
Author: Yiheng Wang
Author-email: yhwang0828@sjtu.edu.cn
License: MIT
License-File: LICENSE
